pangerl_mcp_server_weather/__init__.py
pangerl_mcp_server_weather/server.py
pangerl_mcp_server_weather-0.1.2.dist-info/METADATA
pangerl_mcp_server_weather-0.1.2.dist-info/WHEEL
pangerl_mcp_server_weather-0.1.2.dist-info/entry_points.txt
pangerl_mcp_server_weather-0.1.2.dist-info/RECORD
