Metadata-Version: 2.4
Name: pangerl-mcp-server-weather
Version: 0.1.2
Summary: 天气查询MCP
Author-email: lanpang <hxjagf@gmail.com>
Requires-Python: >=3.13
Requires-Dist: httpx>=0.28.1
Requires-Dist: mcp[cli]>=1.12.1
